{
    "headline": "Vegan Arepas Made with Polenta",
    "name": "Vegan Arepas Made with Polenta",
    "description": "Layers of polenta, tofu, bananas, avocado, and mango salsa combine for a surprising and simple meal.",
    "recipeCuisine": [
        "U.S."
    ],
    "totalTime": "PT35M",
    "cookTime": "PT15M",
    "nutrition": {
        "@type": "NutritionInformation",
        "calories": "563 kcal",
        "carbohydrateContent": "64 g",
        "fiberContent": "15 g",
        "proteinContent": "14 g",
        "saturatedFatContent": "5 g",
        "sodiumContent": "591 mg",
        "sugarContent": "21 g",
        "fatContent": "32 g",
        "unsaturatedFatContent": "0 g"
    },
    "prepTime": "PT20M",
    "recipeCategory": [
        "Dinner",
        "Lunch"
    ],
    "recipeIngredient": [
        "1 (8 ounce) container tofu, drained",
        "1 (16 ounce) tube prepared polenta",
        "olive oil",
        "2 bananas, sliced lengthwise",
        "1 cup black beans, undrained",
        "2 avocados - peeled, pitted, and sliced",
        "1 large mango - peeled, seeded, and diced",
        "0.25 cup diced onion",
        "1 jalapeno pepper, seeded and minced",
        "salt to taste"
    ],
    "recipeInstructions": [
        {
            "@type": "HowToStep",
            "text": "Preheat the oven's broiler and set the oven rack about 6 inches from the heat source. Grease a baking sheet."
        },
        {
            "@type": "HowToStep",
            "text": "Slice the tofu and polenta into slabs of equal thickness; brush with olive oil and arrange on a baking sheet."
        },
        {
            "@type": "HowToStep",
            "text": "Cook the tofu and polenta under the preheated broiler until the tops are crispy, about 5 minutes. Remove from oven and set aside."
        },
        {
            "@type": "HowToStep",
            "text": "Heat the olive oil in a skillet over medium-high heat. Cook the bananas in the oil until crispy on the outside, yet soft on the inside, about 5 minutes. Remove the bananas from the oil and set aside."
        },
        {
            "@type": "HowToStep",
            "text": "Pour the entire can of black beans into a blender and blend until a thick sauce forms."
        },
        {
            "@type": "HowToStep",
            "text": "Stir the mango, diced onion, jalapeno pepper, and salt together in a small bowl."
        },
        {
            "@type": "HowToStep",
            "text": "To build the arepas, place a slice of polenta on each of four plates and top each with first about 1/4 of the bean sauce, then a piece of tofu, a few slices of banana, some avocado, and finishing with about 1/4 of the mango salsa."
        }
    ],
    "recipeYield": [
        "4"
    ]
}