{
    "headline": "Polish Bean and Sausage Stew",
    "name": "Polish Bean and Sausage Stew",
    "description": "A hearty and satisfying Polish stew with cannellini beans, kielbasa, bacon, and tomatoes that sticks to the bones on a cold winter's night.",
    "recipeCuisine": [
        "Polish"
    ],
    "totalTime": "PT565M",
    "cookTime": "PT65M",
    "nutrition": {
        "@type": "NutritionInformation",
        "calories": "817 kcal",
        "carbohydrateContent": "89 g",
        "cholesterolContent": "74 mg",
        "fiberContent": "22 g",
        "proteinContent": "47 g",
        "saturatedFatContent": "14 g",
        "sodiumContent": "1225 mg",
        "sugarContent": "9 g",
        "fatContent": "31 g",
        "unsaturatedFatContent": "0 g"
    },
    "prepTime": "PT20M",
    "recipeCategory": [
        "Dinner"
    ],
    "recipeIngredient": [
        "2.5 cups dry cannellini beans",
        "1 tablespoon vegetable oil",
        "10 slices bacon, cubed",
        "0.5 (16 oz) ring kielbasa sausage, cubed",
        "2 onions, chopped",
        "2 bay leaves",
        "4 whole allspice berries",
        "1 (14.5 ounce) can chopped tomatoes",
        "dried marjoram, or to taste",
        "1 clove garlic, minced",
        "salt and ground black pepper to taste",
        "1 tablespoon butter",
        "1 tablespoon all-purpose flour",
        "1 teaspoon paprika"
    ],
    "recipeInstructions": [
        {
            "@type": "HowToStep",
            "text": "Place cannellini beans into a large container and cover with several inches of cool water; let soak 8 hours to overnight. Drain and add to a large pot. Cover with fresh water and cook on low heat until beans are tender, 45 minutes to 1 hour."
        },
        {
            "@type": "HowToStep",
            "text": "Heat oil in a skillet over medium-high heat while beans are cooking. Add bacon and sausage and cook until browned, 5 to 10 minutes. Transfer meats to a bowl, reserving some of the grease in the skillet."
        },
        {
            "@type": "HowToStep",
            "text": "Cook onions in the reserved grease until browned, 5 to 10 minutes. Add to bowl with meats."
        },
        {
            "@type": "HowToStep",
            "text": "Stir meat mixture, bay leaves, and allspice into the cooked beans and bring to a simmer. Add tomatoes, marjoram, garlic, salt, and pepper and continue to simmer, 10 to 15 minutes. Add water if there is not enough liquid in the pot."
        },
        {
            "@type": "HowToStep",
            "image": [
                {
                    "@type": "ImageObject",
                    "url": "https://www.allrecipes.com/thmb/P9FNjH4kESHxPlcbjSbjtoW2wtQ=/1500x0/filters:no_upscale():max_bytes(150000):strip_icc()/4573370-f959fa8ac6d14f16b41e691f24c45fb8.jpg"
                }
            ],
            "text": "Melt butter in a small saucepan over low heat, add flour, and stir into a paste. Remove from heat and add to stew; stir in paprika powder. Simmer until stew has thickened, about 15 minutes."
        }
    ],
    "recipeYield": [
        "4"
    ]
}