{
    "headline": "Heather's Crawfish Etouffee",
    "name": "Heather's Crawfish Etouffee",
    "description": "Crawfish \u00e9touff\u00e9e is a bold-flavored specialty of Louisiana. It is a simple dish made with long-grain rice, onion, bell pepper, garlic, and crawfish tails.",
    "recipeCuisine": [
        "Southern"
    ],
    "totalTime": "PT50M",
    "cookTime": "PT35M",
    "nutrition": {
        "@type": "NutritionInformation",
        "calories": "703 kcal",
        "carbohydrateContent": "85 g",
        "cholesterolContent": "121 mg",
        "fiberContent": "2 g",
        "proteinContent": "24 g",
        "saturatedFatContent": "5 g",
        "sodiumContent": "856 mg",
        "sugarContent": "4 g",
        "fatContent": "29 g",
        "unsaturatedFatContent": "0 g"
    },
    "prepTime": "PT15M",
    "recipeCategory": [
        "Dinner"
    ],
    "recipeIngredient": [
        "4 cups water",
        "2 cups long grain white rice",
        "0.5 cup margarine",
        "1 large onion, chopped",
        "1 medium green bell pepper, chopped",
        "2 cloves garlic, minced",
        "1 (10.75 ounce) can condensed cream of mushroom soup",
        "0.5 cup water, or as needed",
        "salt and black pepper to taste",
        "cayenne pepper to taste",
        "1 pound peeled crawfish tails"
    ],
    "recipeInstructions": [
        {
            "@type": "HowToStep",
            "text": "Combine 4 cups water and rice in a saucepan; bring to a boil. Cover; reduce heat to low. Simmer until rice is tender and water has been absorbed, 15 to 20 minutes."
        },
        {
            "@type": "HowToStep",
            "text": "While rice is cooking, melt margarine in a large skillet over medium heat. Add onion and bell pepper; cook and stir until tender, 10 to 15 minutes. Stir in garlic; cook 1 minute."
        },
        {
            "@type": "HowToStep",
            "text": "Add cream of mushroom soup and 1/2 cup water to skillet; stir to combine. Season with salt, black pepper, and cayenne pepper; stir in crawfish tails. Cover and reduce heat to low; simmer for 15 to 20 minutes, stirring occasionally. Add water to thin sauce as needed. Serve over rice."
        }
    ],
    "recipeYield": [
        "4"
    ]
}