{
    "headline": "Pig Pickin' Cake",
    "name": "Pig Pickin' Cake",
    "description": "Pig pickin' cake is a wonderful dessert that's easy to make using box mix. Three layers of cake get topped with frozen whipped topping and pineapple.",
    "recipeCuisine": [
        "Southern"
    ],
    "totalTime": "PT45M",
    "cookTime": "PT25M",
    "nutrition": {
        "@type": "NutritionInformation",
        "calories": "524 kcal",
        "carbohydrateContent": "71 g",
        "cholesterolContent": "75 mg",
        "fiberContent": "1 g",
        "proteinContent": "6 g",
        "saturatedFatContent": "12 g",
        "sodiumContent": "523 mg",
        "sugarContent": "51 g",
        "fatContent": "25 g",
        "unsaturatedFatContent": "0 g"
    },
    "prepTime": "PT20M",
    "recipeCategory": [
        "Dessert"
    ],
    "recipeIngredient": [
        "1 (15.25 ounce) package yellow cake mix",
        "1 (11 ounce) can mandarin oranges, juice reserved",
        "4 large eggs",
        "0.25 cup vegetable oil",
        "1 (16 ounce) package frozen whipped topping, thawed",
        "1 (15 ounce) can crushed pineapple, drained",
        "1 (3.5 ounce) package instant vanilla pudding mix"
    ],
    "recipeInstructions": [
        {
            "@type": "HowToStep",
            "image": [
                {
                    "@type": "ImageObject",
                    "url": "https://www.allrecipes.com/thmb/VPDMMGBOq4MVif4YmhLySpRH6EI=/1500x0/filters:no_upscale():max_bytes(150000):strip_icc()/8043-pig-pickin-cake-VAT-step-01-2368fbfc47334c8fb21782c0c251553a.jpg"
                }
            ],
            "text": "Gather all ingredients. Preheat the oven to 350 degrees F (175 degrees C)."
        },
        {
            "@type": "HowToStep",
            "image": [
                {
                    "@type": "ImageObject",
                    "url": "https://www.allrecipes.com/thmb/eZ6iOQ6b9sDYPG2tUat54ge_k-U=/1500x0/filters:no_upscale():max_bytes(150000):strip_icc()/8043-pig-pickin-cake-VAT-step-02-bec33909a8554abbba7322c36722eb63.jpg"
                }
            ],
            "text": "Prepare the cake: Mix together cake mix, mandarin oranges with juice, eggs, and oil. Pour batter into three greased and floured 8-inch round pans. Layers will be thin."
        },
        {
            "@type": "HowToStep",
            "image": [
                {
                    "@type": "ImageObject",
                    "url": "https://www.allrecipes.com/thmb/o2T1NJmlV9JmX0kFBD74dGGguVY=/1500x0/filters:no_upscale():max_bytes(150000):strip_icc()/8043-pig-pickin-cake-VAT-step-03-4f1eace65e894cba8399f6a4158c5d5d.jpg"
                }
            ],
            "text": "Bake in the preheated oven until a toothpick inserted into the center of cake comes out clean, 25 to 30 minutes. Cool layers on wire racks."
        },
        {
            "@type": "HowToStep",
            "image": [
                {
                    "@type": "ImageObject",
                    "url": "https://www.allrecipes.com/thmb/WBNXRWsQL5b0nOnAyoMZS3-qIqQ=/1500x0/filters:no_upscale():max_bytes(150000):strip_icc()/8043-pig-pickin-cake-VAT-step-04-9a067c408aea4effa94a1604683b7d68.jpg"
                }
            ],
            "text": "Make the frosting: Mix together whipped topping, crushed pineapple, and instant pudding mix."
        },
        {
            "@type": "HowToStep",
            "image": [
                {
                    "@type": "ImageObject",
                    "url": "https://www.allrecipes.com/thmb/bRv6X4SfNjQHQ7G-nJpOQ49Xbxc=/1500x0/filters:no_upscale():max_bytes(150000):strip_icc()/8043-pig-pickin-cake-VAT-step-05-af2b9dfbffad4d219e6f2ab2a005431a.jpg"
                }
            ],
            "text": "Spread frosting onto the cooled cake layers. Stack layers; frost top and sides. Refrigerate until ready to eat."
        },
        {
            "@type": "HowToStep",
            "image": [
                {
                    "@type": "ImageObject",
                    "url": "https://www.allrecipes.com/thmb/atimsYpunr6-oWQNEML5FGjRUpE=/1500x0/filters:no_upscale():max_bytes(150000):strip_icc()/8043-pig-pickin-cake-VAT-4x3-2ffa6b1a46064116adf04e4a6b41022d.jpg"
                }
            ],
            "text": "Slice and enjoy!"
        }
    ],
    "recipeYield": [
        "10"
    ]
}